AUTHORS.txt
CHANGES.txt
LICENSE.txt
MANIFEST.in
README.txt
setup.py
tipfy/__init__.py
tipfy.ext.wtforms.egg-info/PKG-INFO
tipfy.ext.wtforms.egg-info/SOURCES.txt
tipfy.ext.wtforms.egg-info/dependency_links.txt
tipfy.ext.wtforms.egg-info/namespace_packages.txt
tipfy.ext.wtforms.egg-info/not-zip-safe
tipfy.ext.wtforms.egg-info/requires.txt
tipfy.ext.wtforms.egg-info/top_level.txt
tipfy/ext/__init__.py
tipfy/ext/wtforms/__init__.py
tipfy/ext/wtforms/fields.py
tipfy/ext/wtforms/form.py
tipfy/ext/wtforms/validators.py
tipfy/ext/wtforms/widgets.py