Metadata-Version: 1.0
Name: tipfy.ext.wtforms
Version: 0.5
Summary: WTForms extension for tipfy
Home-page: http://www.tipfy.org/
Author: Rodrigo Moraes
Author-email: rodrigo.moraes@gmail.com
License: BSD
Platform: any
Classifier: Development Status :: 4 - Beta
Classifier: Environment :: Web Environment
Classifier: Intended Audience :: Developers
Classifier: License :: OSI Approved :: BSD License
Classifier: Operating System :: OS Independent
Classifier: Programming Language :: Python
Classifier: Topic :: Internet :: WWW/HTTP :: Dynamic Content
Classifier: Topic :: Software Development :: Libraries :: Python Modules
